{
    "hits": [
        {
            "project_id": "AANobbMI",
            "project_type": "mod",
            "slug": "sodium",
            "author": "jellysquid3",
            "author_id": "TEZXhE2U",
            "organization": "CaffeineMC",
            "organization_id": "LjcZDkRW",
            "title": "Sodium",
            "description": "The fastest and most compatible rendering optimization mod for Minecraft. Now available for both NeoForge and Fabric!",
            "categories": [
                "fabric",
                "neoforge",
                "optimization",
                "quilt"
            ],
            "display_categories": [
                "fabric",
                "neoforge",
                "optimization",
                "quilt"
            ],
            "versions": [
                "1.16.3",
                "1.16.4",
                "1.16.5",
                "1.17",
                "1.17.1",
                "1.18",
                "1.18.1",
                "1.18.2",
                "1.19",
                "1.19.1",
                "1.19.2",
                "1.19.3",
                "1.19.4",
                "1.20",
                "1.20.1",
                "1.20.2",
                "1.20.3",
                "1.20.4",
                "1.20.5",
                "1.20.6",
                "1.21",
                "1.21.1",
                "1.21.2",
                "1.21.3",
                "1.21.4",
                "1.21.5",
                "1.21.6",
                "1.21.7",
                "1.21.8",
                "1.21.9",
                "1.21.10",
                "1.21.11",
                "26.1",
                "26.1.1",
                "26.1.2"
            ],
            "downloads": 149211708,
            "follows": 35860,
            "icon_url": "https://cdn.modrinth.com/data/AANobbMI/295862f4724dc3f78df3447ad6072b2dcd3ef0c9_96.webp",
            "date_created": "2021-01-03T00:53:34.185936+00:00",
            "date_modified": "2026-04-28T01:14:04.235470+00:00",
            "latest_version": "SIrB5bCM",
            "license": "LicenseRef-Polyform-Shield-1.0.0",
            "client_side": "required",
            "server_side": "unsupported",
            "gallery": [
                "https://cdn.modrinth.com/data/AANobbMI/images/d84313e6f57dc9e7896961dbd2dfc2689d482758_350.webp",
                "https://cdn.modrinth.com/data/AANobbMI/images/6b0e58705156ba67a6d97a74b9f9ac05da69f502_350.webp",
                "https://cdn.modrinth.com/data/AANobbMI/images/b681a9e87daa53a0e85336a894db70427007149b_350.webp",
                "https://cdn.modrinth.com/data/AANobbMI/images/56c4599efcb529a19aed0e118caad4178d7fd540.webp",
                "https://cdn.modrinth.com/data/AANobbMI/images/5ca2e8f6c72f3d543dd3dc95b706964c5678d80e_350.webp",
                "https://cdn.modrinth.com/data/AANobbMI/images/c39debea7fc623306e9c45148084585399fc59ee.webp"
            ],
            "featured_gallery": null,
            "color": 8703084
        },
        {
            "project_id": "PtjYWJkn",
            "project_type": "mod",
            "slug": "sodium-extra",
            "author": "FlashyReese",
            "author_id": "QXAY01zS",
            "organization": null,
            "organization_id": null,
            "title": "Sodium Extra",
            "description": "A Sodium addon that adds features that shouldn't be in Sodium.",
            "categories": [
                "cursed",
                "fabric",
                "neoforge",
                "optimization",
                "quilt",
                "utility"
            ],
            "display_categories": [
                "cursed",
                "fabric",
                "neoforge",
                "optimization",
                "quilt",
                "utility"
            ],
            "versions": [
                "1.16.2",
                "1.16.3",
                "1.16.4",
                "1.16.5",
                "1.17",
                "1.17.1",
                "1.18",
                "1.18.1",
                "1.18.2",
                "1.19",
                "1.19.1",
                "1.19.2",
                "1.19.3",
                "1.19.4",
                "1.20",
                "1.20.1",
                "1.20.2",
                "1.20.3",
                "1.20.4",
                "1.20.5",
                "1.20.6",
                "1.21",
                "1.21.1",
                "1.21.2",
                "1.21.3",
                "1.21.4",
                "1.21.5",
                "1.21.6",
                "1.21.7",
                "1.21.8",
                "1.21.9",
                "1.21.10",
                "1.21.11",
                "26.1",
                "26.1.1",
                "26.1.2"
            ],
            "downloads": 67406308,
            "follows": 12136,
            "icon_url": "https://cdn.modrinth.com/data/PtjYWJkn/0df4fb22a11e1dcb5e83cb0aadd275b571aca7a9_96.webp",
            "date_created": "2021-02-17T04:37:04.928784+00:00",
            "date_modified": "2026-04-10T02:41:36.960976+00:00",
            "latest_version": "1bz3AMCV",
            "license": "LGPL-3.0-only",
            "client_side": "required",
            "server_side": "unsupported",
            "gallery": [],
            "featured_gallery": null,
            "color": 16577485
        },
        {
            "project_id": "Bh37bMuy",
            "project_type": "mod",
            "slug": "reeses-sodium-options",
            "author": "FlashyReese",
            "author_id": "QXAY01zS",
            "organization": null,
            "organization_id": null,
            "title": "Reese's Sodium Options",
            "description": "Alternative Options Menu for Sodium",
            "categories": [
                "fabric",
                "neoforge",
                "quilt",
                "utility"
            ],
            "display_categories": [
                "fabric",
                "neoforge",
                "quilt",
                "utility"
            ],
            "versions": [
                "1.16.5",
                "1.17",
                "1.17.1",
                "1.18",
                "1.18.1",
                "1.18.2",
                "1.19",
                "1.19.1",
                "1.19.2",
                "22w42a",
                "22w43a",
                "22w44a",
                "22w45a",
                "22w46a",
                "1.19.3-pre1",
                "1.19.3-pre2",
                "1.19.3",
                "1.19.4",
                "1.20",
                "1.20.1",
                "1.20.2",
                "1.20.3",
                "1.20.4",
                "1.20.5",
                "1.20.6",
                "1.21",
                "1.21.1",
                "1.21.2",
                "1.21.3",
                "1.21.4",
                "1.21.5",
                "1.21.6",
                "1.21.7",
                "1.21.8",
                "1.21.9",
                "1.21.10",
                "1.21.11",
                "26.1",
                "26.1.1",
                "26.1.2"
            ],
            "downloads": 57295326,
            "follows": 8288,
            "icon_url": "https://cdn.modrinth.com/data/Bh37bMuy/icon.png",
            "date_created": "2021-08-21T06:10:10.242065+00:00",
            "date_modified": "2026-04-04T07:17:23.613983+00:00",
            "latest_version": "p88Tf9YM",
            "license": "MIT",
            "client_side": "required",
            "server_side": "unsupported",
            "gallery": [],
            "featured_gallery": null,
            "color": 6978040
        }
    ],
    "offset": 0,
    "limit": 3,
    "total_hits": 82
}